{
    "dijs": [
        [
            "2017-06-09T10:16:25Z",
            "dijs/wiki",
            "PushEvent"
        ],
        [
            "2017-06-09T10:17:30Z",
            "dijs/wiki",
            "PushEvent"
        ]
    ],
    "jrieken": [
        [
            "2017-06-09T14:12:46Z",
            "Microsoft/vscode",
            "PushEvent"
        ]
    ],
    "mlaursen": [
        [
            "2017-06-09T21:04:57Z",
            "mlaursen/react-md",
            "PushEvent"
        ]
    ],
    "w33ble": [
        [
            "2017-06-09T18:19:44Z",
            "elastic/kibana",
            "PushEvent"
        ]
    ],
    "chrisdopuch": [
        [
            "2017-06-09T17:30:04Z",
            "appnexus/lucid",
            "PushEvent"
        ],
        [
            "2017-06-09T17:36:05Z",
            "appnexus/lucid",
            "PushEvent"
        ],
        [
            "2017-06-09T17:41:42Z",
            "appnexus/lucid",
            "PushEvent"
        ]
    ],
    "flauc": [
        [
            "2017-06-09T12:32:06Z",
            "flauc/angular2-notifications",
            "PushEvent"
        ]
    ],
    "tiii": [
        [
            "2017-06-09T16:17:54Z",
            "tommikaikkonen/redux-orm",
            "PushEvent"
        ]
    ],
    "weotch": [
        [
            "2017-06-09T16:56:27Z",
            "BKWLD/vue-in-viewport-mixin",
            "PushEvent"
        ]
    ],
    "fsmanuel": [
        [
            "2017-06-09T12:04:15Z",
            "funkensturm/ember-local-storage",
            "PushEvent"
        ],
        [
            "2017-06-09T12:17:23Z",
            "funkensturm/ember-local-storage",
            "PushEvent"
        ],
        [
            "2017-06-09T12:34:22Z",
            "funkensturm/ember-local-storage",
            "PushEvent"
        ],
        [
            "2017-06-09T12:35:20Z",
            "funkensturm/ember-local-storage",
            "PushEvent"
        ]
    ],
    "eighteyes": [
        [
            "2017-06-09T19:52:55Z",
            "matrix-io/matrix-cli",
            "PushEvent"
        ],
        [
            "2017-06-09T19:54:07Z",
            "matrix-io/matrix-cli",
            "PushEvent"
        ]
    ],
    "gavofyork": [
        [
            "2017-06-09T10:20:16Z",
            "paritytech/parity",
            "PushEvent"
        ],
        [
            "2017-06-09T10:20:44Z",
            "paritytech/parity",
            "PushEvent"
        ],
        [
            "2017-06-09T10:21:12Z",
            "paritytech/parity",
            "PushEvent"
        ],
        [
            "2017-06-09T10:21:44Z",
            "paritytech/parity",
            "PushEvent"
        ],
        [
            "2017-06-09T10:22:24Z",
            "paritytech/parity",
            "PushEvent"
        ],
        [
            "2017-06-09T10:24:29Z",
            "paritytech/parity",
            "PushEvent"
        ],
        [
            "2017-06-09T10:25:20Z",
            "paritytech/parity",
            "PushEvent"
        ],
        [
            "2017-06-09T10:27:04Z",
            "paritytech/parity",
            "PushEvent"
        ],
        [
            "2017-06-09T10:31:10Z",
            "paritytech/parity",
            "PushEvent"
        ]
    ],
    "tkaemming": [
        [
            "2017-06-09T22:25:37Z",
            "getsentry/sentry",
            "PushEvent"
        ]
    ],
    "Kegsay": [
        [
            "2017-06-09T14:06:15Z",
            "matrix-org/matrix-react-sdk",
            "PushEvent"
        ]
    ],
    "nreese": [
        [
            "2017-06-09T16:52:02Z",
            "elastic/kibana",
            "PushEvent"
        ],
        [
            "2017-06-09T16:52:35Z",
            "elastic/kibana",
            "PushEvent"
        ]
    ],
    "sendilkumarn": [
        [
            "2017-06-09T01:37:16Z",
            "jhipster/generator-jhipster",
            "PushEvent"
        ]
    ],
    "titarenko": [
        [
            "2017-06-09T14:15:03Z",
            "titarenko/fix-phone",
            "PushEvent"
        ],
        [
            "2017-06-09T14:15:27Z",
            "titarenko/fix-phone",
            "PushEvent"
        ]
    ],
    "felixnielsen": [
        [
            "2017-06-09T09:27:30Z",
            "space10-community/conversational-form",
            "PushEvent"
        ]
    ],
    "pedesen": [
        [
            "2017-06-09T09:17:21Z",
            "camunda/camunda-modeler",
            "PushEvent"
        ]
    ],
    "wknet123": [
        [
            "2017-06-09T08:28:52Z",
            "vmware/harbor",
            "PushEvent"
        ]
    ],
    "yusufsafak": [
        [
            "2017-06-09T12:49:33Z",
            "cerebral/cerebral",
            "PushEvent"
        ]
    ],
    "jamuhl": [
        [
            "2017-06-09T09:37:12Z",
            "i18next/react-i18next",
            "PushEvent"
        ],
        [
            "2017-06-09T09:39:39Z",
            "i18next/react-i18next",
            "PushEvent"
        ],
        [
            "2017-06-09T09:40:36Z",
            "i18next/react-i18next",
            "PushEvent"
        ]
    ],
    "dpa99c": [
        [
            "2017-06-09T19:08:19Z",
            "dpa99c/cordova-check-plugins",
            "PushEvent"
        ],
        [
            "2017-06-09T19:28:51Z",
            "dpa99c/cordova-check-plugins",
            "PushEvent"
        ],
        [
            "2017-06-09T19:49:24Z",
            "dpa99c/cordova-check-plugins",
            "PushEvent"
        ]
    ],
    "NejcZdovc": [
        [
            "2017-06-09T17:03:56Z",
            "brave/browser-laptop",
            "PushEvent"
        ],
        [
            "2017-06-09T17:04:53Z",
            "brave/browser-laptop",
            "PushEvent"
        ]
    ],
    "alexandrudima": [
        [
            "2017-06-09T14:13:03Z",
            "Microsoft/vscode",
            "PushEvent"
        ]
    ],
    "General-Beck": [
        [
            "2017-06-09T17:44:46Z",
            "paritytech/parity",
            "PushEvent"
        ]
    ],
    "ian-r-rose": [
        [
            "2017-06-09T18:46:23Z",
            "jupyterlab/jupyterlab",
            "PushEvent"
        ]
    ],
    "retotrinkler": [
        [
            "2017-06-09T15:23:43Z",
            "melonproject/protocol",
            "PushEvent"
        ]
    ],
    "danpat": [
        [
            "2017-06-09T05:02:26Z",
            "Project-OSRM/osrm-backend",
            "PushEvent"
        ]
    ],
    "NekR": [
        [
            "2017-06-09T16:57:58Z",
            "NekR/offline-plugin",
            "PushEvent"
        ]
    ],
    "KyleAMathews": [
        [
            "2017-06-09T01:34:23Z",
            "gatsbyjs/gatsby",
            "PushEvent"
        ]
    ],
    "goto-bus-stop": [
        [
            "2017-06-09T21:12:34Z",
            "u-wave/web",
            "PushEvent"
        ]
    ],
    "jansiegel": [
        [
            "2017-06-09T15:31:56Z",
            "handsontable/handsontable",
            "PushEvent"
        ]
    ],
    "bergos": [
        [
            "2017-06-09T18:00:21Z",
            "rdf-ext/rdf-ext",
            "PushEvent"
        ]
    ],
    "springmeyer": [
        [
            "2017-06-09T14:13:00Z",
            "mapbox/node-pre-gyp",
            "PushEvent"
        ],
        [
            "2017-06-09T14:15:09Z",
            "mapbox/node-pre-gyp",
            "PushEvent"
        ]
    ],
    "christian-bromann": [
        [
            "2017-06-09T09:10:09Z",
            "webdriverio/wdio-spec-reporter",
            "PushEvent"
        ]
    ],
    "zkochan": [
        [
            "2017-06-09T22:11:53Z",
            "pnpm/pnpm",
            "PushEvent"
        ],
        [
            "2017-06-09T22:22:58Z",
            "pnpm/cmd-shim",
            "PushEvent"
        ],
        [
            "2017-06-09T22:37:27Z",
            "pnpm/pnpm",
            "PushEvent"
        ]
    ],
    "scottinet": [
        [
            "2017-06-09T13:01:08Z",
            "kuzzleio/sdk-javascript",
            "PushEvent"
        ],
        [
            "2017-06-09T13:12:51Z",
            "kuzzleio/sdk-javascript",
            "PushEvent"
        ],
        [
            "2017-06-09T13:13:16Z",
            "kuzzleio/sdk-javascript",
            "PushEvent"
        ],
        [
            "2017-06-09T13:29:39Z",
            "kuzzleio/sdk-javascript",
            "PushEvent"
        ],
        [
            "2017-06-09T13:35:04Z",
            "kuzzleio/sdk-javascript",
            "PushEvent"
        ],
        [
            "2017-06-09T13:46:22Z",
            "kuzzleio/sdk-javascript",
            "PushEvent"
        ]
    ],
    "CFPBot": [
        [
            "2017-06-09T21:05:20Z",
            "cfpb/capital-framework",
            "PushEvent"
        ],
        [
            "2017-06-09T21:05:20Z",
            "cfpb/capital-framework",
            "PushEvent"
        ]
    ],
    "MrRob": [
        [
            "2017-06-09T07:19:03Z",
            "headintheclouddev/typings-suitescript-2.0",
            "PushEvent"
        ]
    ],
    "mike-north": [
        [
            "2017-06-09T16:22:53Z",
            "mike-north/ember-data-preload",
            "PushEvent"
        ],
        [
            "2017-06-09T16:33:52Z",
            "mike-north/ember-windoc",
            "PushEvent"
        ]
    ],
    "usergenic": [
        [
            "2017-06-09T06:13:21Z",
            "Polymer/polymer-bundler",
            "PushEvent"
        ]
    ],
    "trygve-lie": [
        [
            "2017-06-09T08:23:06Z",
            "asset-pipe/asset-pipe-js-reader",
            "PushEvent"
        ],
        [
            "2017-06-09T08:47:13Z",
            "asset-pipe/asset-pipe-js-reader",
            "PushEvent"
        ]
    ],
    "ppisljar": [
        [
            "2017-06-09T09:28:19Z",
            "elastic/kibana",
            "PushEvent"
        ]
    ],
    "protonate": [
        [
            "2017-06-09T17:09:22Z",
            "prebid/Prebid.js",
            "PushEvent"
        ]
    ],
    "niklasramo": [
        [
            "2017-06-09T18:14:56Z",
            "haltu/muuri",
            "PushEvent"
        ]
    ],
    "kball": [
        [
            "2017-06-09T23:52:26Z",
            "zurb/foundation-sites",
            "PushEvent"
        ]
    ],
    "GermanBluefox": [
        [
            "2017-06-09T06:14:09Z",
            "ioBroker/ioBroker.hm-rpc",
            "PushEvent"
        ]
    ],
    "andy-ms": [
        [
            "2017-06-09T22:05:55Z",
            "DefinitelyTyped/DefinitelyTyped",
            "PushEvent"
        ]
    ],
    "selfthinker": [
        [
            "2017-06-09T17:07:57Z",
            "alphagov/govuk_elements",
            "PushEvent"
        ]
    ],
    "dbemiller": [
        [
            "2017-06-09T17:57:57Z",
            "prebid/Prebid.js",
            "PushEvent"
        ]
    ],
    "mjbvz": [
        [
            "2017-06-09T23:33:26Z",
            "Microsoft/vscode",
            "PushEvent"
        ]
    ],
    "AndreyBelym": [
        [
            "2017-06-09T15:32:58Z",
            "DevExpress/testcafe",
            "PushEvent"
        ]
    ],
    "jamesdaniels": [
        [
            "2017-06-09T23:10:14Z",
            "firebase/emberfire",
            "PushEvent"
        ]
    ],
    "DzyubSpirit": [
        [
            "2017-06-09T09:03:41Z",
            "metarhia/metasync",
            "PushEvent"
        ],
        [
            "2017-06-09T09:04:22Z",
            "metarhia/metasync",
            "PushEvent"
        ]
    ],
    "bbyars": [
        [
            "2017-06-09T00:02:38Z",
            "bbyars/mountebank",
            "PushEvent"
        ],
        [
            "2017-06-09T00:20:26Z",
            "bbyars/mountebank",
            "PushEvent"
        ]
    ],
    "lykmapipo": [
        [
            "2017-06-09T14:29:09Z",
            "lykmapipo/kue-scheduler",
            "PushEvent"
        ]
    ],
    "dpilafian": [
        [
            "2017-06-09T21:13:12Z",
            "dnajs/dna.js",
            "PushEvent"
        ],
        [
            "2017-06-09T21:14:21Z",
            "dnajs/dna.js",
            "PushEvent"
        ]
    ],
    "TehShrike": [
        [
            "2017-06-09T16:38:44Z",
            "TehShrike/abstract-state-router",
            "PushEvent"
        ]
    ],
    "muaz-khan": [
        [
            "2017-06-09T05:25:46Z",
            "muaz-khan/RecordRTC",
            "PushEvent"
        ]
    ],
    "baudehlo": [
        [
            "2017-06-09T22:25:52Z",
            "haraka/Haraka",
            "PushEvent"
        ],
        [
            "2017-06-09T22:37:34Z",
            "haraka/Haraka",
            "PushEvent"
        ]
    ],
    "leebyron": [
        [
            "2017-06-09T01:31:28Z",
            "facebook/immutable-js",
            "PushEvent"
        ]
    ],
    "linuxwolf": [
        [
            "2017-06-09T15:25:16Z",
            "cisco/node-jose",
            "PushEvent"
        ]
    ],
    "fehguy": [
        [
            "2017-06-09T18:47:25Z",
            "swagger-api/swagger-ui",
            "PushEvent"
        ]
    ],
    "NikVolf": [
        [
            "2017-06-09T15:31:19Z",
            "paritytech/parity",
            "PushEvent"
        ]
    ],
    "yiminghe": [
        [
            "2017-06-09T16:46:52Z",
            "yiminghe/async-validator",
            "PushEvent"
        ],
        [
            "2017-06-09T16:47:05Z",
            "yiminghe/async-validator",
            "PushEvent"
        ],
        [
            "2017-06-09T16:58:49Z",
            "yiminghe/async-validator",
            "PushEvent"
        ]
    ],
    "ehfeng": [
        [
            "2017-06-09T23:03:30Z",
            "getsentry/sentry",
            "PushEvent"
        ]
    ],
    "dbaeumer": [
        [
            "2017-06-09T20:27:45Z",
            "Microsoft/vscode",
            "PushEvent"
        ]
    ],
    "arobson": [
        [
            "2017-06-09T21:02:29Z",
            "npm/npme-installer",
            "PushEvent"
        ],
        [
            "2017-06-09T21:05:07Z",
            "npm/npme-installer",
            "PushEvent"
        ]
    ],
    "Kylart": [
        [
            "2017-06-09T14:29:54Z",
            "Kylart/MalScraper",
            "PushEvent"
        ]
    ],
    "inikolova": [
        [
            "2017-06-09T14:52:54Z",
            "telerik/kendo-theme-default",
            "PushEvent"
        ],
        [
            "2017-06-09T14:58:46Z",
            "telerik/kendo-theme-bootstrap",
            "PushEvent"
        ]
    ],
    "kosanna": [
        [
            "2017-06-09T06:14:37Z",
            "seek-oss/seek-style-guide",
            "PushEvent"
        ]
    ],
    "gkatsev": [
        [
            "2017-06-09T19:07:14Z",
            "videojs/videojs-contrib-hls",
            "PushEvent"
        ]
    ],
    "mjneil": [
        [
            "2017-06-09T20:18:10Z",
            "videojs/videojs-contrib-hls",
            "PushEvent"
        ],
        [
            "2017-06-09T20:20:50Z",
            "videojs/videojs-contrib-hls",
            "PushEvent"
        ]
    ],
    "wilaw": [
        [
            "2017-06-09T21:24:23Z",
            "Dash-Industry-Forum/dash.js",
            "PushEvent"
        ]
    ],
    "adamgruber": [
        [
            "2017-06-09T02:02:05Z",
            "adamgruber/mochawesome",
            "PushEvent"
        ],
        [
            "2017-06-09T02:31:32Z",
            "adamgruber/mochawesome",
            "PushEvent"
        ]
    ],
    "AlexandreBonneau": [
        [
            "2017-06-09T04:21:32Z",
            "autoNumeric/autoNumeric",
            "PushEvent"
        ],
        [
            "2017-06-09T04:23:53Z",
            "autoNumeric/autoNumeric",
            "PushEvent"
        ]
    ],
    "kevinpschaaf": [
        [
            "2017-06-09T12:12:20Z",
            "Polymer/polymer",
            "PushEvent"
        ]
    ],
    "silverwind": [
        [
            "2017-06-09T09:03:03Z",
            "silverwind/droppy",
            "PushEvent"
        ],
        [
            "2017-06-09T09:11:37Z",
            "silverwind/droppy",
            "PushEvent"
        ]
    ],
    "leepowellcouk": [
        [
            "2017-06-09T14:28:24Z",
            "leepowellcouk/mongoose-validator",
            "PushEvent"
        ]
    ],
    "ilanbiala": [
        [
            "2017-06-09T18:11:05Z",
            "twilio/twilio-node",
            "PushEvent"
        ]
    ],
    "rkavalap": [
        [
            "2017-06-09T15:09:53Z",
            "appium/appium",
            "PushEvent"
        ],
        [
            "2017-06-09T15:31:37Z",
            "appium/appium",
            "PushEvent"
        ]
    ],
    "hacksparrow": [
        [
            "2017-06-09T11:52:24Z",
            "strongloop/generator-loopback",
            "PushEvent"
        ]
    ],
    "stevemao": [
        [
            "2017-06-09T22:05:31Z",
            "so-fancy/diff-so-fancy",
            "PushEvent"
        ]
    ],
    "guilleiguaran": [
        [
            "2017-06-09T14:34:09Z",
            "rails/rails",
            "PushEvent"
        ],
        [
            "2017-06-09T14:55:00Z",
            "rails/rails",
            "PushEvent"
        ]
    ],
    "markdalgleish": [
        [
            "2017-06-09T06:20:12Z",
            "seek-oss/seek-style-guide",
            "PushEvent"
        ]
    ],
    "spacetc62": [
        [
            "2017-06-09T19:04:40Z",
            "Losant/losant-rest-js",
            "PushEvent"
        ]
    ],
    "wiredearp": [
        [
            "2017-06-09T12:19:36Z",
            "Tradeshift/tradeshift-ui",
            "PushEvent"
        ],
        [
            "2017-06-09T12:32:40Z",
            "Tradeshift/tradeshift-ui",
            "PushEvent"
        ]
    ],
    "simonguo": [
        [
            "2017-06-09T09:52:21Z",
            "rsuite/rsuite-table",
            "PushEvent"
        ]
    ],
    "mirisuzanne": [
        [
            "2017-06-09T00:21:18Z",
            "oddbird/susy",
            "PushEvent"
        ]
    ],
    "jimmynotjim": [
        [
            "2017-06-09T21:07:57Z",
            "cfpb/capital-framework",
            "PushEvent"
        ],
        [
            "2017-06-09T21:20:47Z",
            "cfpb/capital-framework",
            "PushEvent"
        ],
        [
            "2017-06-09T21:46:04Z",
            "cfpb/capital-framework",
            "PushEvent"
        ]
    ],
    "thomasconner": [
        [
            "2017-06-09T18:13:04Z",
            "Kinvey/js-sdk",
            "PushEvent"
        ],
        [
            "2017-06-09T18:21:37Z",
            "Kinvey/js-sdk",
            "PushEvent"
        ],
        [
            "2017-06-09T18:42:22Z",
            "Kinvey/js-sdk",
            "PushEvent"
        ]
    ],
    "gemmaleigh": [
        [
            "2017-06-09T14:18:59Z",
            "alphagov/govuk_elements",
            "PushEvent"
        ]
    ],
    "darkdh": [
        [
            "2017-06-09T23:38:20Z",
            "brave/browser-laptop",
            "PushEvent"
        ],
        [
            "2017-06-09T23:51:40Z",
            "brave/browser-laptop",
            "PushEvent"
        ]
    ],
    "matthewlane": [
        [
            "2017-06-09T22:20:24Z",
            "prebid/Prebid.js",
            "PushEvent"
        ]
    ],
    "schiehll": [
        [
            "2017-06-09T00:01:09Z",
            "schiehll/react-alert",
            "PushEvent"
        ]
    ],
    "pmuens": [
        [
            "2017-06-09T22:10:05Z",
            "serverless/serverless",
            "PushEvent"
        ]
    ],
    "briancavalier": [
        [
            "2017-06-09T12:08:51Z",
            "mostjs/core",
            "PushEvent"
        ],
        [
            "2017-06-09T12:09:27Z",
            "mostjs/core",
            "PushEvent"
        ]
    ],
    "blink1073": [
        [
            "2017-06-09T17:38:31Z",
            "jupyterlab/jupyterlab",
            "PushEvent"
        ],
        [
            "2017-06-09T17:48:48Z",
            "jupyterlab/jupyterlab",
            "PushEvent"
        ]
    ],
    "brianjgeiger": [
        [
            "2017-06-09T15:58:45Z",
            "CenterForOpenScience/ember-osf",
            "PushEvent"
        ]
    ],
    "brianneisler": [
        [
            "2017-06-09T16:44:15Z",
            "serverless/serverless",
            "PushEvent"
        ]
    ],
    "anselmbradford": [
        [
            "2017-06-09T14:14:15Z",
            "cfpb/capital-framework",
            "PushEvent"
        ]
    ],
    "leo": [
        [
            "2017-06-09T14:43:10Z",
            "zeit/serve",
            "PushEvent"
        ]
    ],
    "ywk253100": [
        [
            "2017-06-09T03:08:12Z",
            "vmware/harbor",
            "PushEvent"
        ]
    ],
    "SheetJSDev": [
        [
            "2017-06-09T02:22:48Z",
            "SheetJS/js-xlsx",
            "PushEvent"
        ]
    ],
    "dpgraham": [
        [
            "2017-06-09T22:04:25Z",
            "appium/appium",
            "PushEvent"
        ],
        [
            "2017-06-09T22:10:16Z",
            "appium/appium",
            "PushEvent"
        ],
        [
            "2017-06-09T22:13:13Z",
            "appium/appium",
            "PushEvent"
        ],
        [
            "2017-06-09T22:15:51Z",
            "appium/appium",
            "PushEvent"
        ],
        [
            "2017-06-09T22:37:39Z",
            "appium/appium",
            "PushEvent"
        ],
        [
            "2017-06-09T22:40:04Z",
            "appium/appium",
            "PushEvent"
        ]
    ],
    "sokra": [
        [
            "2017-06-09T15:13:21Z",
            "webpack/webpack",
            "PushEvent"
        ],
        [
            "2017-06-09T15:13:46Z",
            "webpack/webpack",
            "PushEvent"
        ],
        [
            "2017-06-09T15:14:22Z",
            "webpack/webpack",
            "PushEvent"
        ]
    ],
    "gaearon": [
        [
            "2017-06-09T19:48:43Z",
            "facebook/react-devtools",
            "PushEvent"
        ],
        [
            "2017-06-09T19:49:17Z",
            "facebook/react-devtools",
            "PushEvent"
        ],
        [
            "2017-06-09T19:59:44Z",
            "facebook/react-devtools",
            "PushEvent"
        ]
    ],
    "rayrutjes": [
        [
            "2017-06-09T10:04:25Z",
            "algolia/vue-instantsearch",
            "PushEvent"
        ],
        [
            "2017-06-09T10:09:38Z",
            "algolia/vue-instantsearch",
            "PushEvent"
        ],
        [
            "2017-06-09T10:10:42Z",
            "algolia/vue-instantsearch",
            "PushEvent"
        ],
        [
            "2017-06-09T10:17:33Z",
            "algolia/vue-instantsearch",
            "PushEvent"
        ],
        [
            "2017-06-09T10:52:14Z",
            "algolia/vue-instantsearch",
            "PushEvent"
        ]
    ],
    "mgechev": [
        [
            "2017-06-09T02:01:08Z",
            "mgechev/codelyzer",
            "PushEvent"
        ],
        [
            "2017-06-09T02:06:17Z",
            "mgechev/codelyzer",
            "PushEvent"
        ]
    ],
    "holger1411": [
        [
            "2017-06-09T05:52:23Z",
            "holger1411/understrap",
            "PushEvent"
        ]
    ],
    "balajikris": [
        [
            "2017-06-09T03:46:21Z",
            "Azure/azure-xplat-cli",
            "PushEvent"
        ],
        [
            "2017-06-09T03:50:38Z",
            "Azure/azure-xplat-cli",
            "PushEvent"
        ]
    ],
    "yysun": [
        [
            "2017-06-09T01:56:31Z",
            "yysun/apprun",
            "PushEvent"
        ]
    ],
    "Maciek416": [
        [
            "2017-06-09T20:32:17Z",
            "TestArmada/magellan-saucelabs-executor",
            "PushEvent"
        ]
    ],
    "bpasero": [
        [
            "2017-06-09T16:11:16Z",
            "Microsoft/vscode",
            "PushEvent"
        ],
        [
            "2017-06-09T16:22:53Z",
            "Microsoft/vscode",
            "PushEvent"
        ]
    ],
    "Mitko-Kerezov": [
        [
            "2017-06-09T14:37:50Z",
            "telerik/mobile-cli-lib",
            "PushEvent"
        ]
    ],
    "gcanti": [
        [
            "2017-06-09T10:12:32Z",
            "gcanti/tcomb-form-native",
            "PushEvent"
        ],
        [
            "2017-06-09T10:14:32Z",
            "gcanti/tcomb-form-native",
            "PushEvent"
        ]
    ],
    "LukeSheard": [
        [
            "2017-06-09T22:07:40Z",
            "infernojs/inferno",
            "PushEvent"
        ],
        [
            "2017-06-09T22:40:32Z",
            "infernojs/inferno",
            "PushEvent"
        ]
    ],
    "dnwe": [
        [
            "2017-06-09T10:09:21Z",
            "mqlight/nodejs-mqlight",
            "PushEvent"
        ],
        [
            "2017-06-09T10:26:25Z",
            "mqlight/nodejs-mqlight",
            "PushEvent"
        ],
        [
            "2017-06-09T10:29:43Z",
            "mqlight/nodejs-mqlight",
            "PushEvent"
        ]
    ],
    "bergie": [
        [
            "2017-06-09T09:46:27Z",
            "noflo/noflo-filetype",
            "PushEvent"
        ]
    ],
    "jonschlinkert": [
        [
            "2017-06-09T23:39:59Z",
            "jonschlinkert/randomatic",
            "PushEvent"
        ],
        [
            "2017-06-09T23:40:11Z",
            "jonschlinkert/randomatic",
            "PushEvent"
        ],
        [
            "2017-06-09T23:52:57Z",
            "jonschlinkert/randomatic",
            "PushEvent"
        ]
    ],
    "AlexanderMoskovkin": [
        [
            "2017-06-09T15:29:22Z",
            "DevExpress/testcafe",
            "PushEvent"
        ]
    ],
    "luisrudge": [
        [
            "2017-06-09T20:07:38Z",
            "auth0/lock",
            "PushEvent"
        ],
        [
            "2017-06-09T20:08:09Z",
            "auth0/lock",
            "PushEvent"
        ],
        [
            "2017-06-09T20:21:16Z",
            "auth0/lock",
            "PushEvent"
        ],
        [
            "2017-06-09T20:41:53Z",
            "auth0/lock",
            "PushEvent"
        ]
    ],
    "schneems": [
        [
            "2017-06-09T13:09:44Z",
            "rails/rails",
            "PushEvent"
        ]
    ],
    "christiansmith": [
        [
            "2017-06-09T20:22:10Z",
            "anvilresearch/oidc-rp",
            "PushEvent"
        ],
        [
            "2017-06-09T20:27:18Z",
            "anvilresearch/oidc-rp",
            "PushEvent"
        ],
        [
            "2017-06-09T20:31:11Z",
            "anvilresearch/oidc-rp",
            "PushEvent"
        ]
    ],
    "razvanz": [
        [
            "2017-06-09T11:07:14Z",
            "razvanz/cassandra-store",
            "PushEvent"
        ],
        [
            "2017-06-09T11:10:47Z",
            "razvanz/cassandra-store",
            "PushEvent"
        ],
        [
            "2017-06-09T11:12:37Z",
            "razvanz/cassandra-store",
            "PushEvent"
        ],
        [
            "2017-06-09T11:15:33Z",
            "razvanz/cassandra-store",
            "PushEvent"
        ]
    ],
    "gr2m": [
        [
            "2017-06-09T10:22:59Z",
            "hoodiehq/hoodie",
            "PushEvent"
        ],
        [
            "2017-06-09T10:26:40Z",
            "pouchdb/pouchdb-server",
            "PushEvent"
        ]
    ],
    "anmonteiro": [
        [
            "2017-06-09T20:14:39Z",
            "anmonteiro/lumo",
            "PushEvent"
        ]
    ],
    "Awk34": [
        [
            "2017-06-09T16:04:27Z",
            "angular-fullstack/generator-angular-fullstack",
            "PushEvent"
        ]
    ],
    "cormacmccarthy": [
        [
            "2017-06-09T14:26:29Z",
            "ExactTarget/fuelux",
            "PushEvent"
        ],
        [
            "2017-06-09T14:27:53Z",
            "ExactTarget/fuelux",
            "PushEvent"
        ],
        [
            "2017-06-09T14:28:27Z",
            "ExactTarget/fuelux",
            "PushEvent"
        ],
        [
            "2017-06-09T14:28:47Z",
            "ExactTarget/fuelux",
            "PushEvent"
        ],
        [
            "2017-06-09T14:29:13Z",
            "ExactTarget/fuelux",
            "PushEvent"
        ],
        [
            "2017-06-09T14:29:47Z",
            "ExactTarget/fuelux",
            "PushEvent"
        ],
        [
            "2017-06-09T14:30:15Z",
            "ExactTarget/fuelux",
            "PushEvent"
        ],
        [
            "2017-06-09T14:38:04Z",
            "ExactTarget/fuelux",
            "PushEvent"
        ],
        [
            "2017-06-09T14:38:20Z",
            "ExactTarget/fuelux",
            "PushEvent"
        ]
    ],
    "hshristov": [
        [
            "2017-06-09T11:11:47Z",
            "NativeScript/NativeScript",
            "PushEvent"
        ]
    ],
    "danez": [
        [
            "2017-06-09T21:42:09Z",
            "babel/babylon",
            "PushEvent"
        ]
    ],
    "bsclifton": [
        [
            "2017-06-09T21:02:47Z",
            "brave/browser-laptop",
            "PushEvent"
        ]
    ],
    "oxidase": [
        [
            "2017-06-09T11:20:47Z",
            "Project-OSRM/osrm-backend",
            "PushEvent"
        ]
    ],
    "benoitvidis": [
        [
            "2017-06-09T13:04:57Z",
            "kuzzleio/sdk-javascript",
            "PushEvent"
        ],
        [
            "2017-06-09T13:33:33Z",
            "kuzzleio/sdk-javascript",
            "PushEvent"
        ],
        [
            "2017-06-09T13:39:25Z",
            "kuzzleio/sdk-javascript",
            "PushEvent"
        ]
    ],
    "akameco": [
        [
            "2017-06-09T21:11:50Z",
            "akameco/generator-nm",
            "PushEvent"
        ]
    ],
    "sanniassin": [
        [
            "2017-06-09T20:05:18Z",
            "sanniassin/react-input-mask",
            "PushEvent"
        ],
        [
            "2017-06-09T20:17:48Z",
            "sanniassin/react-input-mask",
            "PushEvent"
        ]
    ],
    "scottleibrand": [
        [
            "2017-06-09T04:09:43Z",
            "openaps/oref0",
            "PushEvent"
        ]
    ],
    "jfhbrook": [
        [
            "2017-06-09T01:00:37Z",
            "jfhbrook/node-ecstatic",
            "PushEvent"
        ],
        [
            "2017-06-09T01:04:32Z",
            "jfhbrook/node-ecstatic",
            "PushEvent"
        ],
        [
            "2017-06-09T01:07:19Z",
            "jfhbrook/node-ecstatic",
            "PushEvent"
        ],
        [
            "2017-06-09T01:36:20Z",
            "jfhbrook/node-ecstatic",
            "PushEvent"
        ]
    ],
    "vkarpov15": [
        [
            "2017-06-09T03:06:52Z",
            "Automattic/mongoose",
            "PushEvent"
        ]
    ],
    "isidorn": [
        [
            "2017-06-09T13:20:33Z",
            "Microsoft/vscode",
            "PushEvent"
        ],
        [
            "2017-06-09T13:39:48Z",
            "Microsoft/vscode",
            "PushEvent"
        ]
    ],
    "eduardoboucas": [
        [
            "2017-06-09T16:08:54Z",
            "dadi/web",
            "PushEvent"
        ]
    ],
    "jdubois": [
        [
            "2017-06-09T14:34:39Z",
            "jhipster/generator-jhipster",
            "PushEvent"
        ]
    ],
    "dmitrizagidulin": [
        [
            "2017-06-09T20:11:53Z",
            "anvilresearch/oidc-rp",
            "PushEvent"
        ],
        [
            "2017-06-09T20:13:15Z",
            "anvilresearch/oidc-rp",
            "PushEvent"
        ]
    ],
    "jheer": [
        [
            "2017-06-09T17:13:45Z",
            "vega/vega",
            "PushEvent"
        ],
        [
            "2017-06-09T17:28:53Z",
            "vega/vega",
            "PushEvent"
        ]
    ],
    "olydis": [
        [
            "2017-06-09T14:45:37Z",
            "Azure/autorest",
            "PushEvent"
        ]
    ],
    "karmacoma": [
        [
            "2017-06-09T10:00:30Z",
            "LiskHQ/lisk",
            "PushEvent"
        ],
        [
            "2017-06-09T10:00:31Z",
            "LiskHQ/lisk",
            "PushEvent"
        ],
        [
            "2017-06-09T10:00:31Z",
            "LiskHQ/lisk",
            "PushEvent"
        ]
    ],
    "sirDonovan": [
        [
            "2017-06-09T01:33:47Z",
            "Zarel/Pokemon-Showdown",
            "PushEvent"
        ]
    ],
    "czardoz": [
        [
            "2017-06-09T13:01:36Z",
            "postmanlabs/postman-collection",
            "PushEvent"
        ]
    ],
    "kwkbtr": [
        [
            "2017-06-09T07:40:17Z",
            "vivliostyle/vivliostyle.js",
            "PushEvent"
        ],
        [
            "2017-06-09T07:50:32Z",
            "vivliostyle/vivliostyle.js",
            "PushEvent"
        ]
    ],
    "cjcenizal": [
        [
            "2017-06-09T05:21:50Z",
            "elastic/kibana",
            "PushEvent"
        ]
    ],
    "marcoow": [
        [
            "2017-06-09T07:10:41Z",
            "simplabs/ember-simple-auth",
            "PushEvent"
        ]
    ],
    "simplyspoke": [
        [
            "2017-06-09T23:32:46Z",
            "log0ymxm/node-harvest",
            "PushEvent"
        ]
    ],
    "laktak": [
        [
            "2017-06-09T20:19:37Z",
            "hjson/hjson-js",
            "PushEvent"
        ]
    ],
    "jhchen": [
        [
            "2017-06-09T20:55:14Z",
            "quilljs/quill",
            "PushEvent"
        ]
    ],
    "vipulnsward": [
        [
            "2017-06-09T12:01:50Z",
            "rails/rails",
            "PushEvent"
        ]
    ],
    "existentialism": [
        [
            "2017-06-09T23:41:37Z",
            "babel/babel",
            "PushEvent"
        ]
    ],
    "Tyriar": [
        [
            "2017-06-09T23:11:20Z",
            "Microsoft/vscode",
            "PushEvent"
        ],
        [
            "2017-06-09T23:18:56Z",
            "Microsoft/vscode",
            "PushEvent"
        ]
    ],
    "gabrielcsapo": [
        [
            "2017-06-09T17:28:31Z",
            "local-npm/local-npm",
            "PushEvent"
        ]
    ],
    "novemberborn": [
        [
            "2017-06-09T17:17:45Z",
            "avajs/ava",
            "PushEvent"
        ]
    ],
    "deltakosh": [
        [
            "2017-06-09T23:18:45Z",
            "BabylonJS/Babylon.js",
            "PushEvent"
        ]
    ],
    "rebornix": [
        [
            "2017-06-09T23:56:57Z",
            "Microsoft/vscode",
            "PushEvent"
        ]
    ],
    "bbondy": [
        [
            "2017-06-09T13:08:50Z",
            "brave/browser-laptop",
            "PushEvent"
        ],
        [
            "2017-06-09T13:09:32Z",
            "brave/browser-laptop",
            "PushEvent"
        ]
    ],
    "alexlamsl": [
        [
            "2017-06-09T17:09:01Z",
            "mishoo/UglifyJS2",
            "PushEvent"
        ]
    ],
    "michelkaporin": [
        [
            "2017-06-09T14:16:38Z",
            "Microsoft/vscode",
            "PushEvent"
        ]
    ],
    "mayacoda": [
        [
            "2017-06-09T15:37:25Z",
            "rabix/cwl-ts",
            "PushEvent"
        ],
        [
            "2017-06-09T15:46:28Z",
            "rabix/cwl-ts",
            "PushEvent"
        ],
        [
            "2017-06-09T15:49:22Z",
            "rabix/cwl-ts",
            "PushEvent"
        ]
    ],
    "macqueen": [
        [
            "2017-06-09T22:37:32Z",
            "getsentry/sentry",
            "PushEvent"
        ],
        [
            "2017-06-09T22:50:51Z",
            "getsentry/sentry",
            "PushEvent"
        ]
    ],
    "nschonni": [
        [
            "2017-06-09T16:49:20Z",
            "sass/node-sass",
            "PushEvent"
        ]
    ],
    "sgratzl": [
        [
            "2017-06-09T14:28:17Z",
            "phovea/phovea_core",
            "PushEvent"
        ]
    ],
    "kauegimenes": [
        [
            "2017-06-09T16:31:09Z",
            "kauegimenes/jsonexport",
            "PushEvent"
        ]
    ],
    "shockey": [
        [
            "2017-06-09T23:46:47Z",
            "swagger-api/swagger-js",
            "PushEvent"
        ]
    ],
    "jhermsmeier": [
        [
            "2017-06-09T12:01:46Z",
            "resin-io-modules/drivelist",
            "PushEvent"
        ]
    ],
    "GianlucaGuarini": [
        [
            "2017-06-09T12:54:10Z",
            "riot/riot",
            "PushEvent"
        ]
    ],
    "wtrocki": [
        [
            "2017-06-09T11:53:22Z",
            "feedhenry/fh-sync-js",
            "PushEvent"
        ]
    ],
    "paularmstrong": [
        [
            "2017-06-09T17:01:25Z",
            "paularmstrong/normalizr",
            "PushEvent"
        ]
    ],
    "brettsmason": [
        [
            "2017-06-09T18:41:22Z",
            "zurb/foundation-sites",
            "PushEvent"
        ]
    ],
    "mariusandra": [
        [
            "2017-06-09T07:27:02Z",
            "namespace-ee/react-calendar-timeline",
            "PushEvent"
        ],
        [
            "2017-06-09T07:38:27Z",
            "namespace-ee/react-calendar-timeline",
            "PushEvent"
        ],
        [
            "2017-06-09T07:41:27Z",
            "namespace-ee/react-calendar-timeline",
            "PushEvent"
        ],
        [
            "2017-06-09T07:49:28Z",
            "namespace-ee/react-calendar-timeline",
            "PushEvent"
        ]
    ],
    "bitnenfer": [
        [
            "2017-06-09T19:15:27Z",
            "photonstorm/phaser",
            "PushEvent"
        ]
    ],
    "tclindner": [
        [
            "2017-06-09T00:15:39Z",
            "tclindner/npm-package-json-lint",
            "PushEvent"
        ]
    ],
    "Andarist": [
        [
            "2017-06-09T08:59:32Z",
            "redux-saga/redux-saga",
            "PushEvent"
        ]
    ],
    "arkpar": [
        [
            "2017-06-09T13:54:49Z",
            "paritytech/parity",
            "PushEvent"
        ]
    ],
    "steven-zou": [
        [
            "2017-06-09T08:33:45Z",
            "vmware/harbor",
            "PushEvent"
        ]
    ],
    "FrancescoCioria": [
        [
            "2017-06-09T19:13:23Z",
            "buildo/react-components",
            "PushEvent"
        ],
        [
            "2017-06-09T19:18:15Z",
            "buildo/react-components",
            "PushEvent"
        ]
    ],
    "swistach": [
        [
            "2017-06-09T12:36:11Z",
            "handsontable/handsontable",
            "PushEvent"
        ],
        [
            "2017-06-09T12:45:06Z",
            "handsontable/handsontable",
            "PushEvent"
        ],
        [
            "2017-06-09T12:47:06Z",
            "handsontable/handsontable",
            "PushEvent"
        ],
        [
            "2017-06-09T12:49:25Z",
            "handsontable/handsontable",
            "PushEvent"
        ]
    ],
    "tfili": [
        [
            "2017-06-09T18:52:19Z",
            "AnalyticalGraphicsInc/cesium",
            "PushEvent"
        ]
    ],
    "imbcmdth": [
        [
            "2017-06-09T21:26:57Z",
            "videojs/videojs-contrib-hls",
            "PushEvent"
        ]
    ],
    "jchip": [
        [
            "2017-06-09T17:43:59Z",
            "electrode-io/electrode",
            "PushEvent"
        ]
    ],
    "jakubpawlowicz": [
        [
            "2017-06-09T11:19:24Z",
            "jakubpawlowicz/clean-css",
            "PushEvent"
        ]
    ],
    "marisaleung": [
        [
            "2017-06-09T23:26:06Z",
            "google/blockly",
            "PushEvent"
        ],
        [
            "2017-06-09T23:54:38Z",
            "google/blockly",
            "PushEvent"
        ]
    ],
    "maciejhirsz": [
        [
            "2017-06-09T14:54:46Z",
            "paritytech/parity",
            "PushEvent"
        ]
    ],
    "SvetoslavTsenov": [
        [
            "2017-06-09T13:36:42Z",
            "NativeScript/NativeScript",
            "PushEvent"
        ],
        [
            "2017-06-09T13:37:18Z",
            "NativeScript/NativeScript",
            "PushEvent"
        ]
    ],
    "futagoza": [
        [
            "2017-06-09T20:52:35Z",
            "pegjs/pegjs",
            "PushEvent"
        ]
    ],
    "boygirl": [
        [
            "2017-06-09T00:04:09Z",
            "FormidableLabs/victory-core",
            "PushEvent"
        ]
    ],
    "kosssi": [
        [
            "2017-06-09T15:03:03Z",
            "cozy/cozy-ui",
            "PushEvent"
        ],
        [
            "2017-06-09T15:10:55Z",
            "cozy/cozy-ui",
            "PushEvent"
        ],
        [
            "2017-06-09T15:25:46Z",
            "cozy/cozy-ui",
            "PushEvent"
        ],
        [
            "2017-06-09T15:29:15Z",
            "cozy/cozy-ui",
            "PushEvent"
        ],
        [
            "2017-06-09T15:49:29Z",
            "cozy/cozy-ui",
            "PushEvent"
        ],
        [
            "2017-06-09T15:51:56Z",
            "cozy/cozy-ui",
            "PushEvent"
        ]
    ],
    "jondlm": [
        [
            "2017-06-09T17:45:57Z",
            "appnexus/lucid",
            "PushEvent"
        ],
        [
            "2017-06-09T17:47:33Z",
            "appnexus/lucid",
            "PushEvent"
        ]
    ],
    "lilleyse": [
        [
            "2017-06-09T14:37:59Z",
            "AnalyticalGraphicsInc/cesium",
            "PushEvent"
        ]
    ],
    "ariya": [
        [
            "2017-06-09T12:00:13Z",
            "jquery/esprima",
            "PushEvent"
        ]
    ],
    "karissa": [
        [
            "2017-06-09T23:14:16Z",
            "datproject/dat",
            "PushEvent"
        ],
        [
            "2017-06-09T23:17:46Z",
            "datproject/dat",
            "PushEvent"
        ],
        [
            "2017-06-09T23:24:13Z",
            "datproject/dat",
            "PushEvent"
        ],
        [
            "2017-06-09T23:29:15Z",
            "datproject/dat",
            "PushEvent"
        ]
    ],
    "psiinon": [
        [
            "2017-06-09T15:22:35Z",
            "zaproxy/zaproxy",
            "PushEvent"
        ]
    ],
    "macdonst": [
        [
            "2017-06-09T03:45:17Z",
            "phonegap/phonegap-plugin-push",
            "PushEvent"
        ]
    ],
    "emackey": [
        [
            "2017-06-09T14:49:27Z",
            "AnalyticalGraphicsInc/cesium",
            "PushEvent"
        ]
    ],
    "es128": [
        [
            "2017-06-09T17:14:41Z",
            "strongloop/fsevents",
            "PushEvent"
        ]
    ],
    "grey-stripe": [
        [
            "2017-06-09T21:21:21Z",
            "stripe/stripe-node",
            "PushEvent"
        ]
    ],
    "tianyong90": [
        [
            "2017-06-09T09:21:28Z",
            "tianyong90/we-vue",
            "PushEvent"
        ]
    ],
    "dbkr": [
        [
            "2017-06-09T21:08:18Z",
            "matrix-org/matrix-react-sdk",
            "PushEvent"
        ],
        [
            "2017-06-09T21:13:56Z",
            "matrix-org/matrix-react-sdk",
            "PushEvent"
        ],
        [
            "2017-06-09T21:17:38Z",
            "vector-im/riot-web",
            "PushEvent"
        ],
        [
            "2017-06-09T21:23:21Z",
            "vector-im/riot-web",
            "PushEvent"
        ]
    ],
    "jaiminpanchal27": [
        [
            "2017-06-09T19:45:03Z",
            "prebid/Prebid.js",
            "PushEvent"
        ]
    ],
    "lpinca": [
        [
            "2017-06-09T12:29:50Z",
            "MONEI/Shopify-api-node",
            "PushEvent"
        ],
        [
            "2017-06-09T12:40:48Z",
            "MONEI/Shopify-api-node",
            "PushEvent"
        ]
    ],
    "diegomura": [
        [
            "2017-06-09T05:31:39Z",
            "diegomura/react-pdf",
            "PushEvent"
        ]
    ],
    "reasonerjt": [
        [
            "2017-06-09T07:28:16Z",
            "vmware/harbor",
            "PushEvent"
        ]
    ],
    "maxbrunsfeld": [
        [
            "2017-06-09T00:03:10Z",
            "atom/superstring",
            "PushEvent"
        ],
        [
            "2017-06-09T00:20:08Z",
            "atom/superstring",
            "PushEvent"
        ]
    ],
    "geografa": [
        [
            "2017-06-09T22:39:07Z",
            "mapbox/mapbox-sdk-js",
            "PushEvent"
        ]
    ],
    "LucasIsasmendi": [
        [
            "2017-06-09T15:05:41Z",
            "LiskHQ/lisk",
            "PushEvent"
        ]
    ],
    "Zarel": [
        [
            "2017-06-09T20:36:53Z",
            "Zarel/Pokemon-Showdown",
            "PushEvent"
        ]
    ],
    "ramya-rao-a": [
        [
            "2017-06-09T22:24:09Z",
            "Microsoft/vscode",
            "PushEvent"
        ]
    ],
    "jakesjews": [
        [
            "2017-06-09T19:28:08Z",
            "lytics/ember-data-model-fragments",
            "PushEvent"
        ]
    ],
    "rafaelfranca": [
        [
            "2017-06-09T20:08:20Z",
            "rails/rails",
            "PushEvent"
        ],
        [
            "2017-06-09T20:19:59Z",
            "rails/rails",
            "PushEvent"
        ]
    ],
    "TooTallNate": [
        [
            "2017-06-09T21:21:10Z",
            "TooTallNate/node-pac-proxy-agent",
            "PushEvent"
        ],
        [
            "2017-06-09T21:21:44Z",
            "TooTallNate/node-pac-proxy-agent",
            "PushEvent"
        ]
    ],
    "mafintosh": [
        [
            "2017-06-09T09:01:58Z",
            "datproject/dat",
            "PushEvent"
        ]
    ],
    "rakuista": [
        [
            "2017-06-09T19:03:27Z",
            "imgix/imgix.js",
            "PushEvent"
        ]
    ],
    "brandur-stripe": [
        [
            "2017-06-09T23:28:17Z",
            "stripe/stripe-node",
            "PushEvent"
        ]
    ],
    "mattwchun": [
        [
            "2017-06-09T21:01:46Z",
            "vega/vega-lite",
            "PushEvent"
        ]
    ],
    "mramato": [
        [
            "2017-06-09T14:56:05Z",
            "AnalyticalGraphicsInc/cesium",
            "PushEvent"
        ]
    ],
    "pjcozzi": [
        [
            "2017-06-09T20:03:53Z",
            "AnalyticalGraphicsInc/cesium",
            "PushEvent"
        ],
        [
            "2017-06-09T20:10:17Z",
            "AnalyticalGraphicsInc/cesium",
            "PushEvent"
        ]
    ],
    "kanitw": [
        [
            "2017-06-09T18:24:41Z",
            "vega/vega-lite",
            "PushEvent"
        ],
        [
            "2017-06-09T18:25:17Z",
            "vega/vega-lite",
            "PushEvent"
        ],
        [
            "2017-06-09T18:36:14Z",
            "vega/vega-lite",
            "PushEvent"
        ]
    ],
    "brollb": [
        [
            "2017-06-09T22:49:53Z",
            "NetsBlox/NetsBlox",
            "PushEvent"
        ]
    ],
    "sebavan": [
        [
            "2017-06-09T17:09:16Z",
            "BabylonJS/Babylon.js",
            "PushEvent"
        ]
    ],
    "szymonkups": [
        [
            "2017-06-09T09:16:37Z",
            "ckeditor/ckeditor5-engine",
            "PushEvent"
        ]
    ],
    "SebastianM": [
        [
            "2017-06-09T21:01:56Z",
            "SebastianM/angular-google-maps",
            "PushEvent"
        ],
        [
            "2017-06-09T21:02:48Z",
            "SebastianM/angular-google-maps",
            "PushEvent"
        ],
        [
            "2017-06-09T21:03:21Z",
            "SebastianM/angular-google-maps",
            "PushEvent"
        ],
        [
            "2017-06-09T21:18:48Z",
            "SebastianM/angular-google-maps",
            "PushEvent"
        ]
    ],
    "photonstorm": [
        [
            "2017-06-09T16:31:22Z",
            "photonstorm/phaser",
            "PushEvent"
        ]
    ],
    "orthagonal": [
        [
            "2017-06-09T00:12:42Z",
            "firstandthird/micro-metrics",
            "PushEvent"
        ]
    ],
    "charlierudolph": [
        [
            "2017-06-09T19:01:17Z",
            "cucumber/cucumber-js",
            "PushEvent"
        ],
        [
            "2017-06-09T19:50:30Z",
            "cucumber/cucumber-js",
            "PushEvent"
        ],
        [
            "2017-06-09T19:51:04Z",
            "cucumber/cucumber-js",
            "PushEvent"
        ]
    ],
    "travs": [
        [
            "2017-06-09T22:05:14Z",
            "melonproject/protocol",
            "PushEvent"
        ]
    ],
    "sorvell": [
        [
            "2017-06-09T01:38:52Z",
            "Polymer/polymer",
            "PushEvent"
        ]
    ],
    "sandy081": [
        [
            "2017-06-09T13:35:48Z",
            "Microsoft/vscode",
            "PushEvent"
        ]
    ],
    "tomscholz": [
        [
            "2017-06-09T08:05:20Z",
            "Dogfalo/materialize",
            "PushEvent"
        ]
    ],
    "pubkey": [
        [
            "2017-06-09T22:02:27Z",
            "pubkey/rxdb",
            "PushEvent"
        ]
    ],
    "arshaw": [
        [
            "2017-06-09T23:59:23Z",
            "fullcalendar/fullcalendar",
            "PushEvent"
        ]
    ],
    "magento-team": [
        [
            "2017-06-09T21:31:10Z",
            "magento/magento2",
            "PushEvent"
        ]
    ],
    "rosen-vladimirov": [
        [
            "2017-06-09T09:45:17Z",
            "telerik/mobile-cli-lib",
            "PushEvent"
        ]
    ],
    "vjeux": [
        [
            "2017-06-09T00:10:04Z",
            "prettier/prettier",
            "PushEvent"
        ]
    ],
    "arnaudbesnier": [
        [
            "2017-06-09T12:42:13Z",
            "ForestAdmin/forest-express-sequelize",
            "PushEvent"
        ]
    ],
    "amilajack": [
        [
            "2017-06-09T18:23:54Z",
            "chentsulin/electron-react-boilerplate",
            "PushEvent"
        ]
    ],
    "alonsogarciapablo": [
        [
            "2017-06-09T14:40:25Z",
            "CartoDB/cartodb.js",
            "PushEvent"
        ]
    ],
    "avwo": [
        [
            "2017-06-09T15:23:13Z",
            "avwo/whistle",
            "PushEvent"
        ]
    ],
    "kellyselden": [
        [
            "2017-06-09T06:14:02Z",
            "tomdale/ember-cli-addon-tests",
            "PushEvent"
        ]
    ],
    "rwholey-eb": [
        [
            "2017-06-09T22:04:07Z",
            "eventbrite/britecharts",
            "PushEvent"
        ],
        [
            "2017-06-09T22:16:24Z",
            "eventbrite/britecharts",
            "PushEvent"
        ],
        [
            "2017-06-09T22:46:05Z",
            "eventbrite/britecharts",
            "PushEvent"
        ],
        [
            "2017-06-09T22:49:49Z",
            "eventbrite/britecharts",
            "PushEvent"
        ]
    ],
    "zkat": [
        [
            "2017-06-09T05:18:01Z",
            "npm/npm",
            "PushEvent"
        ],
        [
            "2017-06-09T05:18:23Z",
            "npm/npm",
            "PushEvent"
        ],
        [
            "2017-06-09T05:19:34Z",
            "npm/npm",
            "PushEvent"
        ]
    ],
    "AidasK": [
        [
            "2017-06-09T10:13:57Z",
            "flowjs/flow.js",
            "PushEvent"
        ]
    ],
    "guidokessels": [
        [
            "2017-06-09T21:04:43Z",
            "guidokessels/xwing-data",
            "PushEvent"
        ],
        [
            "2017-06-09T21:05:41Z",
            "guidokessels/xwing-data",
            "PushEvent"
        ]
    ],
    "nikgraf": [
        [
            "2017-06-09T15:27:20Z",
            "serverless/serverless",
            "PushEvent"
        ]
    ],
    "stephenmcd": [
        [
            "2017-06-09T02:54:18Z",
            "googlemaps/google-maps-services-js",
            "PushEvent"
        ],
        [
            "2017-06-09T02:54:56Z",
            "googlemaps/google-maps-services-js",
            "PushEvent"
        ]
    ],
    "hamidzr": [
        [
            "2017-06-09T17:22:35Z",
            "NetsBlox/NetsBlox",
            "PushEvent"
        ],
        [
            "2017-06-09T17:35:38Z",
            "NetsBlox/NetsBlox",
            "PushEvent"
        ],
        [
            "2017-06-09T17:59:15Z",
            "NetsBlox/NetsBlox",
            "PushEvent"
        ]
    ],
    "pleerock": [
        [
            "2017-06-09T09:13:08Z",
            "typeorm/typeorm",
            "PushEvent"
        ]
    ],
    "prdn": [
        [
            "2017-06-09T12:43:50Z",
            "bitfinexcom/grenache-grape",
            "PushEvent"
        ]
    ],
    "mwittig": [
        [
            "2017-06-09T17:02:13Z",
            "mwittig/node-milight-promise",
            "PushEvent"
        ]
    ],
    "legomushroom": [
        [
            "2017-06-09T03:25:18Z",
            "legomushroom/mojs",
            "PushEvent"
        ]
    ],
    "chasenlehara": [
        [
            "2017-06-09T17:58:19Z",
            "canjs/can-connect",
            "PushEvent"
        ]
    ],
    "diracdeltas": [
        [
            "2017-06-09T00:53:30Z",
            "brave/browser-laptop",
            "PushEvent"
        ]
    ],
    "jeffreysbrother": [
        [
            "2017-06-09T18:49:15Z",
            "jeffreysbrother/generator-ninthlink",
            "PushEvent"
        ],
        [
            "2017-06-09T18:52:15Z",
            "jeffreysbrother/generator-ninthlink",
            "PushEvent"
        ]
    ],
    "cezaraugusto": [
        [
            "2017-06-09T05:08:23Z",
            "brave/browser-laptop",
            "PushEvent"
        ],
        [
            "2017-06-09T05:09:01Z",
            "brave/browser-laptop",
            "PushEvent"
        ],
        [
            "2017-06-09T05:21:49Z",
            "brave/browser-laptop",
            "PushEvent"
        ]
    ],
    "asturur": [
        [
            "2017-06-09T07:56:29Z",
            "kangax/fabric.js",
            "PushEvent"
        ],
        [
            "2017-06-09T07:58:39Z",
            "kangax/fabric.js",
            "PushEvent"
        ]
    ],
    "ekmartin": [
        [
            "2017-06-09T01:32:49Z",
            "ekmartin/slack-irc",
            "PushEvent"
        ],
        [
            "2017-06-09T01:33:01Z",
            "reactiflux/discord-irc",
            "PushEvent"
        ]
    ],
    "stanislav-grin": [
        [
            "2017-06-09T10:02:09Z",
            "Backendless/JS-SDK",
            "PushEvent"
        ]
    ],
    "bigtimebuddy": [
        [
            "2017-06-09T15:22:01Z",
            "pixijs/pixi.js",
            "PushEvent"
        ]
    ],
    "tecfu": [
        [
            "2017-06-09T23:40:32Z",
            "tecfu/tty-table",
            "PushEvent"
        ]
    ],
    "napiergit": [
        [
            "2017-06-09T09:47:12Z",
            "jembi/md-form-builder",
            "PushEvent"
        ]
    ],
    "ara4n": [
        [
            "2017-06-09T21:19:24Z",
            "matrix-org/matrix-react-sdk",
            "PushEvent"
        ],
        [
            "2017-06-09T21:20:19Z",
            "matrix-org/matrix-react-sdk",
            "PushEvent"
        ],
        [
            "2017-06-09T21:22:28Z",
            "vector-im/riot-web",
            "PushEvent"
        ]
    ],
    "hzoo": [
        [
            "2017-06-09T22:12:22Z",
            "babel/babel",
            "PushEvent"
        ],
        [
            "2017-06-09T22:42:58Z",
            "babel/babel",
            "PushEvent"
        ]
    ],
    "dcramer": [
        [
            "2017-06-09T19:08:52Z",
            "getsentry/sentry",
            "PushEvent"
        ],
        [
            "2017-06-09T19:09:42Z",
            "getsentry/sentry",
            "PushEvent"
        ]
    ],
    "pjosh": [
        [
            "2017-06-09T07:48:16Z",
            "Vizzuality/gfw-assets",
            "PushEvent"
        ],
        [
            "2017-06-09T07:49:48Z",
            "Vizzuality/gfw-assets",
            "PushEvent"
        ],
        [
            "2017-06-09T07:51:42Z",
            "Vizzuality/gfw-assets",
            "PushEvent"
        ]
    ],
    "arose": [
        [
            "2017-06-09T06:03:47Z",
            "arose/ngl",
            "PushEvent"
        ],
        [
            "2017-06-09T06:15:01Z",
            "arose/ngl",
            "PushEvent"
        ]
    ],
    "Isabello": [
        [
            "2017-06-09T16:06:45Z",
            "LiskHQ/lisk",
            "PushEvent"
        ]
    ],
    "BergWerkGIS": [
        [
            "2017-06-09T12:21:22Z",
            "mapbox/node-pre-gyp",
            "PushEvent"
        ]
    ],
    "nicolaslopezj": [
        [
            "2017-06-09T19:05:15Z",
            "nicolaslopezj/simple-react-form",
            "PushEvent"
        ],
        [
            "2017-06-09T19:08:25Z",
            "nicolaslopezj/simple-react-form",
            "PushEvent"
        ],
        [
            "2017-06-09T19:09:32Z",
            "nicolaslopezj/simple-react-form",
            "PushEvent"
        ]
    ],
    "Khaledgarbaya": [
        [
            "2017-06-09T07:17:27Z",
            "contentful/contentful.js",
            "PushEvent"
        ],
        [
            "2017-06-09T07:18:57Z",
            "contentful/contentful.js",
            "PushEvent"
        ],
        [
            "2017-06-09T07:22:18Z",
            "contentful/contentful.js",
            "PushEvent"
        ]
    ],
    "vakrilov": [
        [
            "2017-06-09T14:14:25Z",
            "NativeScript/NativeScript",
            "PushEvent"
        ],
        [
            "2017-06-09T14:19:11Z",
            "NativeScript/NativeScript",
            "PushEvent"
        ]
    ],
    "maraoz": [
        [
            "2017-06-09T22:31:21Z",
            "OpenZeppelin/zeppelin-solidity",
            "PushEvent"
        ]
    ],
    "n1474335": [
        [
            "2017-06-09T15:01:45Z",
            "gchq/CyberChef",
            "PushEvent"
        ],
        [
            "2017-06-09T15:21:55Z",
            "gchq/CyberChef",
            "PushEvent"
        ],
        [
            "2017-06-09T15:30:48Z",
            "gchq/CyberChef",
            "PushEvent"
        ],
        [
            "2017-06-09T15:37:07Z",
            "gchq/CyberChef",
            "PushEvent"
        ],
        [
            "2017-06-09T15:43:08Z",
            "gchq/CyberChef",
            "PushEvent"
        ]
    ],
    "evansiroky": [
        [
            "2017-06-09T19:54:35Z",
            "conveyal/modeify",
            "PushEvent"
        ]
    ],
    "wk3368": [
        [
            "2017-06-09T16:09:28Z",
            "easemob/web-im",
            "PushEvent"
        ]
    ],
    "rphmeier": [
        [
            "2017-06-09T16:07:03Z",
            "paritytech/parity",
            "PushEvent"
        ]
    ],
    "robotlolita": [
        [
            "2017-06-09T23:54:46Z",
            "origamitower/folktale",
            "PushEvent"
        ]
    ],
    "contolini": [
        [
            "2017-06-09T21:02:57Z",
            "cfpb/capital-framework",
            "PushEvent"
        ],
        [
            "2017-06-09T21:39:10Z",
            "cfpb/capital-framework",
            "PushEvent"
        ]
    ],
    "lukebarnard1": [
        [
            "2017-06-09T09:54:47Z",
            "matrix-org/matrix-react-sdk",
            "PushEvent"
        ]
    ],
    "toish": [
        [
            "2017-06-09T18:18:06Z",
            "toish/chromatism",
            "PushEvent"
        ]
    ],
    "MaxPresman": [
        [
            "2017-06-09T02:27:09Z",
            "pubnub/javascript",
            "PushEvent"
        ],
        [
            "2017-06-09T02:28:04Z",
            "pubnub/javascript",
            "PushEvent"
        ],
        [
            "2017-06-09T02:28:24Z",
            "pubnub/javascript",
            "PushEvent"
        ],
        [
            "2017-06-09T02:38:28Z",
            "pubnub/javascript",
            "PushEvent"
        ],
        [
            "2017-06-09T02:41:35Z",
            "pubnub/javascript",
            "PushEvent"
        ],
        [
            "2017-06-09T02:42:02Z",
            "pubnub/javascript",
            "PushEvent"
        ],
        [
            "2017-06-09T02:46:41Z",
            "pubnub/javascript",
            "PushEvent"
        ]
    ],
    "buzzdecafe": [
        [
            "2017-06-09T14:51:47Z",
            "ramda/ramda",
            "PushEvent"
        ]
    ],
    "ysugimoto": [
        [
            "2017-06-09T08:12:34Z",
            "ysugimoto/aws-lambda-image",
            "PushEvent"
        ]
    ],
    "danmarshall": [
        [
            "2017-06-09T22:43:40Z",
            "Microsoft/BotFramework-WebChat",
            "PushEvent"
        ],
        [
            "2017-06-09T22:52:05Z",
            "Microsoft/BotFramework-WebChat",
            "PushEvent"
        ]
    ],
    "Apollon77": [
        [
            "2017-06-09T14:12:13Z",
            "ioBroker/ioBroker.geofency",
            "PushEvent"
        ]
    ],
    "weltenwort": [
        [
            "2017-06-09T18:08:14Z",
            "elastic/kibana",
            "PushEvent"
        ]
    ],
    "fengmk2": [
        [
            "2017-06-09T05:27:05Z",
            "alibaba/node-hbase-client",
            "PushEvent"
        ]
    ],
    "bkeepers": [
        [
            "2017-06-09T23:35:43Z",
            "probot/stale",
            "PushEvent"
        ],
        [
            "2017-06-09T23:38:25Z",
            "probot/stale",
            "PushEvent"
        ]
    ],
    "simonihmig": [
        [
            "2017-06-09T17:42:42Z",
            "kaliber5/ember-bootstrap",
            "PushEvent"
        ]
    ],
    "twada": [
        [
            "2017-06-09T14:41:05Z",
            "power-assert-js/empower",
            "PushEvent"
        ],
        [
            "2017-06-09T14:49:34Z",
            "power-assert-js/empower",
            "PushEvent"
        ]
    ],
    "daniel-j-h": [
        [
            "2017-06-09T15:12:51Z",
            "Project-OSRM/osrm-backend",
            "PushEvent"
        ]
    ],
    "sis0k0": [
        [
            "2017-06-09T17:54:49Z",
            "NativeScript/NativeScript",
            "PushEvent"
        ]
    ],
    "diego-G": [
        [
            "2017-06-09T16:15:39Z",
            "LiskHQ/lisk",
            "PushEvent"
        ]
    ],
    "BMartinos": [
        [
            "2017-06-09T08:47:50Z",
            "jembi/md-form-builder",
            "PushEvent"
        ]
    ]
}